src/__init__.py
src/__version__.py
src/app.py
src/abi/WAGMI.py
src/abi/__init__.py
src/abi/sWAGMI.py
src/abi/staking.py
src/helpers/__init__.py
src/helpers/config_helper.py
src/helpers/spinner_helper.py
src/helpers/token_price.py
src/helpers/web3Helper.py
src/service/__init__.py
src/service/dashboard_service.py
src/service/stake_service.py
src/store/__init__.py
src/store/euphoriaData.py
src/store/userData.py
tests/__init__.py
tests/test_dashboard_service.py
tests/test_euphoria_data.py
tests/test_stake_service.py
tests/test_token_price.py
tests/test_user_data.py
Euphoria_CLI-0.3.0.dist-info/LICENSE
Euphoria_CLI-0.3.0.dist-info/METADATA
Euphoria_CLI-0.3.0.dist-info/WHEEL
Euphoria_CLI-0.3.0.dist-info/entry_points.txt
Euphoria_CLI-0.3.0.dist-info/top_level.txt
Euphoria_CLI-0.3.0.dist-info/RECORD
