Metadata-Version: 2.1
Name: Euphoria-CLI
Version: 0.3.0
Summary: A small CLI tool to fetch Euphoria's price and stats
Home-page: https://github.com/vinaydawani/euphoria-cli
Author: Vinay Dawani
Author-email: vdawani6@gmail.com
License: GNU GPL v3
Keywords: euphoria WAGMI sWAGMI blockchain rebase token bonding staking bond stake
Platform: UNKNOWN
Classifier: License :: OSI Approved :: GNU General Public License v3 (GPLv3)
Classifier: Programming Language :: Python :: 3
Classifier: Programming Language :: Python :: 3.9
Classifier: Environment :: Console
Classifier: Natural Language :: English
Requires-Python: >=3.7
License-File: LICENSE
Requires-Dist: Click
Requires-Dist: art
Requires-Dist: requests
Requires-Dist: web3
Requires-Dist: halo
